{
  "panels": [
    {
      "site": "home",
      "id": "GeneralInformation",
      "col": 2,
      "row": 1,
      "colSize": 4,
      "rowSize": 2,
      "interactive": false
    },
    {
      "site": "info",
      "id": "GeneralInformation",
      "col": 0,
      "row": 0,
      "colSize": 4,
      "rowSize": 2,
      "interactive": false
    },
    {
      "site": "info",
      "id": "NavInformation",
      "col": 0,
      "row": 3,
      "colSize": 8,
      "rowSize": 1,
      "interactive": false
    },
    {
      "site": "info",
      "id": "StillUnderDevelopment",
      "col": 0,
      "row": 2,
      "colSize": 8,
      "rowSize": 1,
      "interactive": false
    },
    {
      "site": "setting-user",
      "id": "UserAdministration",
      "col": 2,
      "row": 1,
      "colSize": 4,
      "rowSize": 2,
      "interactive": false
    },
    {
      "site": "setting-config-database",
      "id": "DatabaseInfo",
      "col": 0,
      "row": 0,
      "colSize": 3,
      "rowSize": 4,
      "interactive": false
    },
    {
      "site": "setting-config-database",
      "id": "Import",
      "col": 4,
      "row": 0,
      "colSize": 2,
      "rowSize": 4,
      "interactive": false
    },
    {
      "site": "setting-config-database",
      "id": "Export",
      "col": 6,
      "row": 0,
      "colSize": 2,
      "rowSize": 4,
      "interactive": false
    },
    {
      "site": "setting-devices",
      "id": "DeviceList",
      "col": 2,
      "row": 1,
      "colSize": 4,
      "rowSize": 2,
      "interactive": false
    },
    {
      "site": "TEMPORARY",
      "id": "Temporary",
      "col": 2,
      "row": 1,
      "colSize": 4,
      "rowSize": 2,
      "interactive": false
    }
  ]
}
